cloudinvoke/__init__.py
cloudinvoke-0.1.1.dist-info/licenses/LICENSE
cloudinvoke-0.1.1.dist-info/METADATA
cloudinvoke-0.1.1.dist-info/WHEEL
cloudinvoke-0.1.1.dist-info/top_level.txt
cloudinvoke-0.1.1.dist-info/RECORD
